LICENSE
MANIFEST.in
README.md
setup.py
django_welcome.egg-info/PKG-INFO
django_welcome.egg-info/SOURCES.txt
django_welcome.egg-info/dependency_links.txt
django_welcome.egg-info/requires.txt
django_welcome.egg-info/top_level.txt
welcome/__init__.py
welcome/models.py
welcome/tests.py
welcome/views.py
welcome/management/__init__.py
welcome/management/commands/__init__.py
welcome/management/commands/welcome.py